[
  {"name":"Piel Naranja",
    "height":0.60,
    "width":0.60,
    "price":280,
    "type":"revestimiento",
    "image":"img/Piel Naranja revestimiento.jpg"
  },
  {"name":"Sol",
    "height":0.60,
    "width":0.60,
    "price":280,
    "type":"revestimiento",
    "image":"img/Sol revestimiento.jpg"
  },
  {"name":"Sol con Marco",
    "height":0.60,
    "width":0.60,
    "price":280,
    "type":"revestimiento",
    "image":"img/Sol con Marco revestimiento.jpg"
  },
  {"name":"Ubeda",
    "height":0.60,
    "width":0.60,
    "price":280,
    "type":"revestimiento",
    "image":"img/Ubeda revestimiento.jpg"
  },
  {"name":"Mediterraneo",
    "height":0.60,
    "width":0.60,
    "price":280,
    "type":"revestimiento",
    "image":"img/Mediterraneo revestimiento.jpg"
  },
  {"name":"Liso",
    "height":0.60,
    "width":0.60,
    "price":280,
    "type":"revestimiento",
    "image":"img/Liso revestimiento.jpg"
  },
  {"name":"Travertino",
    "height":0.28,
    "width":0.56,
    "price":175,
    "type":"revestimiento",
    "image":"img/Travertino revestimiento.jpg"
  },
  {"name":"Piedra",
    "height":0.28,
    "width":0.56,
    "price":175,
    "type":"revestimiento",
    "image":"img/Piedra revestimiento.jpg"
  },
  {"name":"Pizarra",
    "height":0.56,
    "width":0.56,
    "price":335,
    "type":"revestimiento",
    "image":"img/Pizarra revestimiento.jpg"
  },
  {"name":"Ladrillo",
    "height":0.56,
    "width":0.56,
    "price":335,
    "type":"revestimiento",
    "image":"img/Ladrillo revestimiento.jpg"
  },
  {"name":"Alicante",
    "height":0.60,
    "width":0.60,
    "price":335,
    "type":"revestimiento",
    "image":"img/Alicante revestimiento.jpg"
  },
  {"name":"Sol",
    "height":0.60,
    "width":0.60,
    "price":335,
    "type":"cielorraso",
    "image":"img/Sol cielorraso.jpg"
  },
  {"name":"Mediterraneo",
    "height":0.60,
    "width":0.60,
    "price":335,
    "type":"cielorraso",
    "image":"img/Mediterraneo cielorraso.jpg"
  },
  {"name":"Alicante",
    "height":0.60,
    "width":0.60,
    "price":335,
    "type":"cielorraso",
    "image":"img/Alicante cielorraso.jpg"
  },
  {"name":"Moldura 9",
    "height":0.04,
    "width":0.05,
    "price":195,
    "type":"Moldura",
    "image":"img/Moldura 9 dise単o.jpg"
  },
  {"name":"Moldura 13",
    "height":0.04,
    "width":0.05,
    "price":195,
    "type":"Moldura",
    "image":"img/Moldura 13 dise単o.jpg"
  },
  {"name":"Friso 1",
    "height":0.04,
    "width":0.01,
    "price":135,
    "type":"Friso",
    "image":"img/Friso 1 dise単o.jpg"
  },
  {"name":"Friso 2",
    "height":0.04,
    "width":0.01,
    "price":135,
    "type":"Friso",
    "image":"img/Friso 2 dise単o.jpg"
  },
  {"name":"Adhesivo",
    "qty":30,
    "price":1100,
    "performance":15,
    "type":"Adhesivo",
    "image":"img/Adhesivo.jpg"
  },
  {"name":"2en1",
    "qty":20,
    "price":1740,
    "performance":15,
    "type":"Adh - Sell",
    "image":"img/2en1.jpg"
  },
  {"name":"Sellajuntas",
    "qty":20,
    "price":1115,
    "performance":25,
    "type":"Sellajuntas",
    "image":"img/Sellajuntas.jpg"
  }
]